{ "height":10,
 "layers":[
        {
         "data":[1, 1, 1, 1, 1, 1, 1, 1, 1, 1, 1, 1, 1, 1, 1, 1, 1, 1, 1, 1, 1, 1, 1, 1, 1, 1, 1, 1, 1, 1, 1, 1, 1, 2, 2, 2, 2, 2, 2, 2, 1, 1, 1, 2, 1, 1, 1, 1, 1, 1, 1, 1, 1, 2, 1, 1, 1, 1, 1, 1, 2, 2, 2, 2, 1, 1, 1, 1, 1, 1, 1, 1, 1, 1, 1, 1, 1, 1, 1, 1, 1, 1, 1, 1, 1, 1, 1, 1, 1, 1, 1, 1, 1, 1, 1, 1, 1, 1, 1, 1],
         "height":10,
         "name":"Kachelebene 1",
         "opacity":1,
         "type":"tilelayer",
         "visible":true,
         "width":10,
         "x":0,
         "y":0
        }],
 "nextobjectid":1,
 "orientation":"isometric",
 "properties":
    {

    },
 "renderorder":"left-up",
 "tileheight":48,
 "tilesets":[
        {
         "firstgid":1,
         "margin":0,
         "name":"std",
         "properties":
            {

            },
         "spacing":0,
         "tileheight":48,
         "tiles":
            {
             "0":
                {
                 "image":"..\/Graphics\/tiles\/grass.png"
                },
             "1":
                {
                 "image":"..\/Graphics\/tiles\/grassdirt.png"
                }
            },
         "tilewidth":96
        }],
 "tilewidth":96,
 "version":1,
 "width":10
}